cursedspace/__init__.py
cursedspace/application.py
cursedspace/colors.py
cursedspace/grid.py
cursedspace/inputline.py
cursedspace/key.py
cursedspace/panel.py
cursedspace/progress.py
cursedspace/scrollpanel.py
cursedspace/shellcontext.py
cursedspace/version.py
cursedspace/docs/cursedspace.html
cursedspace-1.5.2.data/data/share/doc/cursedspace/examples/bars.py
cursedspace-1.5.2.data/data/share/doc/cursedspace/examples/completion.py
cursedspace-1.5.2.data/data/share/doc/cursedspace/examples/grid.py
cursedspace-1.5.2.data/data/share/man/man3/cursedspace.3
cursedspace-1.5.2.dist-info/AUTHORS.md
cursedspace-1.5.2.dist-info/LICENSE
cursedspace-1.5.2.dist-info/METADATA
cursedspace-1.5.2.dist-info/WHEEL
cursedspace-1.5.2.dist-info/entry_points.txt
cursedspace-1.5.2.dist-info/top_level.txt
cursedspace-1.5.2.dist-info/RECORD
