Metadata-Version: 2.1
Name: cursedspace
Version: 1.5.2
Summary: Library for TUI programs on basis of curses
Home-page: https://vonshednob.cc/cursedspace
Author: R
Author-email: contact+cursedspace@vonshednob.cc
License: UNKNOWN
Platform: UNKNOWN
Classifier: Development Status :: 3 - Alpha
Classifier: Environment :: Console :: Curses
Classifier: Intended Audience :: Developers
Classifier: License :: OSI Approved :: MIT License
Classifier: Programming Language :: Python :: 3
Requires-Python: >=3.8
